Workbook

Sheet README
A1: Crypto Transaction Monitoring Case Study
A3: A complete, single-case walkthrough of a crypto exchange transaction-monitoring program — from customer onboarding through alert investigation to a risk-based disposition. Built entirely in Excel formulas. No Python, no SQL, no VBA.
A5: DATA NOTE: the customer, all wallet addresses, and 'Chain Analytics Co' (the wallet-screening vendor) are entirely fictional. No real person, wallet, or blockchain analytics company is referenced.
A7: How to use this workbook — the sheets are ordered to match the actual case lifecycle:
A8: 1. 'Customer_Profile' — what the customer told the exchange at onboarding (KYC).
A9: 2. 'Platform_Activity' — what the customer actually did on the platform, month by month.
A10: 3. 'TM_Alert' — the transaction-monitoring alert that triggered on this activity.
A11: 4. 'Wallet_Risk_Screening' — third-party blockchain analytics results for every external wallet the customer's funds touched.
A12: 5. 'Investigation_Workpaper' — the analytical engine: profile vs. actual activity variance, payment-channel analysis, structuring detection, wallet risk integration, a computed case risk score, and the final risk-based disposition. Every number here is a live formula.
A14: The core investigative question this case study answers: does what this customer actually did on the platform match what they told the exchange they would do — and if not, by how much, and does the destination of the funds make that gap explainable or alarming?
A16: Key formulas used (all standard Excel, no add-ins, no VBA):
A17: - SUMIFS with date-range criteria — computing monthly deposit totals from a flat transaction list, for the profile-vs-actual comparison.
... A21: - Conditional formatting — flagging the Severe/High risk wallet rows directly in the data.

Sheet Customer_Profile
A1: Customer Profile (KYC at Onboarding)
A3: customer_id | B3: CX-2025-0847
A4: customer_name | B4: Alex Mercer
A5: date_of_birth | B5: 1989-04-12
A6: country_of_residence | B6: United States
A7: occupation | B7: Freelance Graphic Designer
A8: stated_source_of_funds | B8: Freelance/consulting income
A9: stated_purpose_of_account | B9: Personal investment in cryptocurrency
A10: stated_expected_monthly_volume_min_usd | B10: 4000
A11: stated_expected_monthly_volume_max_usd | B11: 6000
A12: onboarding_date | B12: 2025-08-01
A13: initial_risk_rating | B13: Medium
A14: id_verification_method | B14: Government ID + Liveness Check
A15: declared_personal_wallet_address | B15: 0x94ac26f9b7f9fab8dea8003a11452eee891e77f5
A16: declared_wallet_verification | B16: Ownership verified via signed message challenge at onboarding

Sheet Platform_Activity
A1: transaction_id | B1: date | C1: type | D1: asset | E1: amount_usd | F1: method_or_counterparty | G1: notes
A2: TX-001 | B2: 45872 | C2: Fiat Deposit | D2: USD | E2: 2000 | F2: ACH Bank Transfer
A3: TX-002 | B3: 45874 | C3: Crypto Buy | D3: BTC | E3: 1800 | F3: Platform Trade
A4: TX-003 | B4: 45889 | C4: Fiat Deposit | D4: USD | E4: 2500 | F4: ACH Bank Transfer
A5: TX-004 | B5: 45891 | C5: Crypto Buy | D5: ETH | E5: 2200 | F5: Platform Trade
A6: TX-005 | B6: 45902 | C6: Fiat Deposit | D6: USD | E6: 3000 | F6: ACH Bank Transfer
A7: TX-006 | B7: 45904 | C7: Crypto Buy | D7: BTC | E7: 2800 | F7: Platform Trade
A8: TX-007 | B8: 45918 | C8: Fiat Deposit | D8: USD | E8: 2000 | F8: ACH Bank Transfer
A9: TX-008 | B9: 45919 | C9: Crypto Withdrawal | D9: BTC | E9: 1900 | F9: 0x94ac26f9b7f9fab8dea8003a11452eee891e77f5 | G9: To declared personal wallet
A10: TX-009 | B10: 45931 | C10: Fiat Deposit | D10: USD | E10: 3500 | F10: ACH Bank Transfer
A11: TX-010 | B11: 45933 | C11: Crypto Buy | D11: ETH | E11: 3200 | F11: Platform Trade
A12: TX-011 | B12: 45945 | C12: Fiat Deposit | D12: USD | E12: 2800 | F12: ACH Bank Transfer
A13: TX-012 | B13: 45946 | C13: Crypto Buy | D13: BTC | E13: 2600 | F13: Platform Trade
A14: TX-013 | B14: 45958 | C14: Crypto Withdrawal | D14: ETH | E14: 2400 | F14: 0x94ac26f9b7f9fab8dea8003a11452eee891e77f5 | G14: To declared personal wallet
A15: TX-014 | B15: 45964 | C15: Fiat Deposit | D15: USD | E15: 9500 | F15: Wire Transfer | G15: Payment method change: first wire, not ACH
A16: TX-015 | B16: 45965 | C16: Fiat Deposit | D16: USD | E16: 9800 | F16: Wire Transfer
A17: TX-016 | B17: 45966 | C17: Fiat Deposit | D17: USD | E17: 9200 | F17: Wire Transfer
A18: TX-017 | B18: 45967 | C18: Fiat Deposit | D18: USD | E18: 15000 | F18: Wire Transfer
A19: TX-018 | B19: 45968 | C19: Fiat Deposit | D19: USD | E19: 12000 | F19: Wire Transfer
A20: TX-019 | B20: 45969 | C20: Fiat Deposit | D20: USD | E20: 9900 | F20: Wire Transfer
A21: TX-020 | B21: 45971 | C21: Fiat Deposit | D21: USD | E21: 19600 | F21: Wire Transfer
A22: TX-021 | B22: 45972 | C22: Crypto Buy | D22: BTC | E22: 40000 | F22: Platform Trade
A23: TX-022 | B23: 45972 | C23: Crypto Buy | D23: ETH | E23: 35000 | F23: Platform Trade
A24: TX-023 | B24: 45973 | C24: Crypto Withdrawal | D24: BTC | E24: 38000 | F24: 0xd32fca24e8114256e8f422605e62ecba47a580f2 | G24: To previously unseen external wallet
A25: TX-024 | B25: 45974 | C25: Crypto Withdrawal | D25: ETH | E25: 33500 | F25: 0xe56abba9fc5b65775b78642c79c1db2db930f65f | G25: To previously unseen external wallet
A26: TX-025 | B26: 45974 | C26: Crypto Withdrawal | D26: BTC | E26: 2000 | F26: 0x94ac26f9b7f9fab8dea8003a11452eee891e77f5 | G26: To declared personal wallet

Sheet TM_Alert
A1: Transaction-Monitoring Alert
A3: alert_id | B3: TM-ALERT-88213
A4: alert_date | B4: 2025-11-14
A5: alert_type | B5: Deposit Velocity + Adverse Wallet Screening (Combined Rule)
A6: triggering_rule_1 | B6: Monthly deposit volume > 300% of rolling 3-month average
A7: triggering_rule_2 | B7: Withdrawal to wallet with Chain Analytics Co risk score >= 70 (High/Severe)
A8: transactions_involved | B8: TX-014 through TX-025
A9: alert_priority | B9: High
A10: assigned_analyst | B10: Jordan Ellis

Sheet Wallet_Risk_Screening
A1: wallet_address | B1: screening_provider | C1: risk_score | D1: risk_category | E1: exposure_type | F1: last_screened_date
A2: 0x94ac26f9b7f9fab8dea8003a11452eee891e77f5 | B2: Chain Analytics Co | C2: 5 | D2: Low | E2: None - customer-attributed wallet, ownership verified | F2: 2025-11-14
A3: 0xd32fca24e8114256e8f422605e62ecba47a580f2 | B3: Chain Analytics Co | C3: 97 | D3: Severe | E3: Direct: Darknet Marketplace | F3: 2025-11-14
A4: 0xe56abba9fc5b65775b78642c79c1db2db930f65f | B4: Chain Analytics Co | C4: 74 | D4: High | E4: Indirect: Mixing Service (2 hops) | F4: 2025-11-14

Sheet Investigation_Workpaper
A1: Investigation Workpaper
A3: 1. Profile vs. Actual Activity
A4: Stated expected monthly volume (min) | B4: =Customer_Profile!B10 -> 4000
A5: Stated expected monthly volume (max) | B5: =Customer_Profile!B11 -> 6000
A6: Actual deposit volume — August 2025 | B6: =SUMIFS(Platform_Activity!$E$2:$E$26,Platform_Activity!$C$2:$C$26,"Fiat Deposit",Platform_Activity!$B$2:$B$26,">="&DATE(2025,8,1),Platform_Activity!$B$2:$B$26,"<="&DATE(2025,8,31)) -> 4500
A7: Actual deposit volume — September 2025 | B7: =SUMIFS(Platform_Activity!$E$2:$E$26,Platform_Activity!$C$2:$C$26,"Fiat Deposit",Platform_Activity!$B$2:$B$26,">="&DATE(2025,9,1),Platform_Activity!$B$2:$B$26,"<="&DATE(2025,9,30)) -> 5000
A8: Actual deposit volume — October 2025 | B8: =SUMIFS(Platform_Activity!$E$2:$E$26,Platform_Activity!$C$2:$C$26,"Fiat Deposit",Platform_Activity!$B$2:$B$26,">="&DATE(2025,10,1),Platform_Activity!$B$2:$B$26,"<="&DATE(2025,10,31)) -> 6300
A9: 3-month rolling average (Aug–Oct) | B9: =AVERAGE(B6:B8) -> 5266.6667
A10: Actual deposit volume — November 2025 (alert month) | B10: =SUMIFS(Platform_Activity!$E$2:$E$26,Platform_Activity!$C$2:$C$26,"Fiat Deposit",Platform_Activity!$B$2:$B$26,">="&DATE(2025,11,1),Platform_Activity!$B$2:$B$26,"<="&DATE(2025,11,30)) -> 85000
A11: November variance vs. 3-month average | B11: =(B10-B9)/B9 -> 15.139241
A12: Flag: volume deviation > 300% of average? | B12: =IF(B11>3,"YES - SEVERE DEVIATION","NO") -> YES - SEVERE DEVIATION
A14: 2. Payment Channel Analysis
A15: ACH deposits, Aug–Oct (baseline channel) | B15: =COUNTIFS(Platform_Activity!$F$2:$F$26,"ACH Bank Transfer",Platform_Activity!$B$2:$B$26,"<"&DATE(2025,11,1)) -> 6
A16: Wire deposits, November (new channel) | B16: =COUNTIFS(Platform_Activity!$F$2:$F$26,"Wire Transfer",Platform_Activity!$B$2:$B$26,">="&DATE(2025,11,1)) -> 7
A17: Flag: new, higher-limit payment channel introduced with volume spike? | B17: =IF(AND(B15>0,B16>0),"YES","NO") -> YES
A19: 3. Structuring Analysis
A20: November deposits between $9,000–$9,999.99 | B20: =COUNTIFS(Platform_Activity!$C$2:$C$26,"Fiat Deposit",Platform_Activity!$E$2:$E$26,">=9000",Platform_Activity!$E$2:$E$26,"<10000",Platform_Activity!$B$2:$B$26,">="&DATE(2025,11,1)) -> 4
A21: Flag: 3+ deposits clustered just under $10,000? | B21: =IF(B20>=3,"YES - POSSIBLE STRUCTURING","NO") -> YES - POSSIBLE STRUCTURING
A23: 4. Wallet Analysis — November Crypto Withdrawals
A24: transaction_id | B24: destination_wallet | C24: amount_usd | D24: risk_category | E24: exposure_type
A25: TX-023 | B25: 0xd32fca24e8114256e8f422605e62ecba47a580f2 | C25: 38000 | D25: =INDEX(Wallet_Risk_Screening!$D$2:$D$4,MATCH(B25,Wallet_Risk_Screening!$A$2:$A$4,0)) -> Severe | E25: =INDEX(Wallet_Risk_Screening!$E$2:$E$4,MATCH(B25,Wallet_Risk_Screening!$A$2:$A$4,0)) -> Direct: Darknet Marketplace
A26: TX-024 | B26: 0xe56abba9fc5b65775b78642c79c1db2db930f65f | C26: 33500 | D26: =INDEX(Wallet_Risk_Screening!$D$2:$D$4,MATCH(B26,Wallet_Risk_Screening!$A$2:$A$4,0)) -> High | E26: =INDEX(Wallet_Risk_Screening!$E$2:$E$4,MATCH(B26,Wallet_Risk_Screening!$A$2:$A$4,0)) -> Indirect: Mixing Service (2 hops)
A27: TX-025 | B27: 0x94ac26f9b7f9fab8dea8003a11452eee891e77f5 | C27: 2000 | D27: =INDEX(Wallet_Risk_Screening!$D$2:$D$4,MATCH(B27,Wallet_Risk_Screening!$A$2:$A$4,0)) -> Low | E27: =INDEX(Wallet_Risk_Screening!$E$2:$E$4,MATCH(B27,Wallet_Risk_Screening!$A$2:$A$4,0)) -> None - customer-attributed wallet, ownership verified
A29: Worst wallet risk category among November withdrawals | B29: =IF(COUNTIF(D25:D27,"Severe")>0,"Severe",IF(COUNTIF(D25:D27,"High")>0,"High",IF(COUNTIF(D25:D27,"Medium")>0,"Medium","Low"))) -> Severe
A31: 5. Case Risk Score & Disposition
A32: Points — volume deviation flag | B32: =IF(B12="YES - SEVERE DEVIATION",40,0) -> 40
A33: Points — worst wallet risk category | B33: =IF(B29="Severe",40,IF(B29="High",25,IF(B29="Medium",10,0))) -> 40
A34: Points — structuring flag | B34: =IF(B21="YES - POSSIBLE STRUCTURING",15,0) -> 15
A35: Points — payment channel shift flag | B35: =IF(B17="YES",10,0) -> 10
A36: TOTAL CASE RISK SCORE | B36: =SUM(B32:B35) -> 105
A37: RISK-BASED DISPOSITION | B37: =IF(B36>=70,"HIGH RISK — File SAR; restrict withdrawals pending review; escalate for law enforcement referral consideration",IF(B36>=40,"MEDIUM-HIGH — Enhanced Due Diligence required; request RFI; senior analyst review","LOW-MEDIUM — Continue standard monitoring")) -> HIGH RISK — File SAR; restrict withdrawals pending review; escalate for law enforcement referral consideration
